kareem_machine_ctrl/__init__.py
kareem_machine_ctrl/config.py
kareem_machine_ctrl/monitoring.py
kareem_machine_ctrl/server.py
kareem_machine_ctrl/api/__init__.py
kareem_machine_ctrl/core/__init__.py
kareem_machine_ctrl/tools/__init__.py
kareem_machine_ctrl/tools/app/__init__.py
kareem_machine_ctrl/tools/browser/__init__.py
kareem_machine_ctrl/tools/shell/__init__.py
kareem_machine_ctrl/tools/system/__init__.py
kareem_machine_ctrl/utils/__init__.py
kareem_machine_ctrl-0.2.0.dist-info/METADATA
kareem_machine_ctrl-0.2.0.dist-info/WHEEL
kareem_machine_ctrl-0.2.0.dist-info/entry_points.txt
kareem_machine_ctrl-0.2.0.dist-info/RECORD
