Metadata-Version: 2.4
Name: kareem-machine-ctrl
Version: 0.2.0
Summary: Sample MCP integration project
Author-email: Kareem Elbahrawy <kareem@kareemelbahrawy.com>
Requires-Python: >=3.10
Requires-Dist: aiohttp>=3.9.0
Requires-Dist: asyncio>=3.4.3
Requires-Dist: click>=8.1.0
Requires-Dist: mcp[cli]>=1.2.1
Requires-Dist: psutil>=5.9.0
Requires-Dist: pyautogui>=0.9.54
Requires-Dist: pydantic-settings>=2.1.0
Requires-Dist: pydantic>=2.0.0
Requires-Dist: python-dotenv>=1.0.0
Requires-Dist: starlette>=0.36.0
Requires-Dist: structlog>=24.1.0
Requires-Dist: uvicorn>=0.27.0
